MANIFEST.in
README.md
setup.cfg
setup.py
pyconfirmdeployment/__init__.py
pyconfirmdeployment/confirm.py
pyconfirmdeployment.egg-info/PKG-INFO
pyconfirmdeployment.egg-info/SOURCES.txt
pyconfirmdeployment.egg-info/dependency_links.txt
pyconfirmdeployment.egg-info/requires.txt
pyconfirmdeployment.egg-info/top_level.txt