Metadata-Version: 1.1
Name: pyconfirmdeployment
Version: 0.0.1
Summary: A python package that can be installed with pip.
Home-page: https://github.com/hanneshapke/pyconfirmdeployment
Author: Hannes Hapke
Author-email: hannes.hapke@gmail.com
License: BSD
Download-URL: https://github.com/hanneshapke/pyconfirmdeployment/tarball/0.0.1
Platform: UNKNOWN
Classifier: Development Status :: 3 - Alpha
Classifier: Intended Audience :: Developers
Classifier: Programming Language :: Python :: 3
